carl/CaRL.py
carl/__init__.py
carl/Tracks/BigMap.png
carl/Tracks/Map3.png
carl/Tracks/MapWithTrinagleAndSquare.png
carl/Tracks/TestTrack.png
car_rl-0.0.2.dist-info/LICENSE
car_rl-0.0.2.dist-info/METADATA
car_rl-0.0.2.dist-info/WHEEL
car_rl-0.0.2.dist-info/top_level.txt
car_rl-0.0.2.dist-info/RECORD
