Metadata-Version: 2.1
Name: car-rl
Version: 0.0.2
Summary: Car game for reinforcement learning
Home-page: https://github.com/MatthiasSchinzel/CaRL
Author: Matthias Schinzel
Author-email: unused@unused.com
License: MIT
Platform: UNKNOWN
Requires-Dist: opencv-python (>=4)
Requires-Dist: numpy (>=1)
Requires-Dist: pygame (>=1)
